CONTRIBUTING.rst
LICENSE
MANIFEST.in
README.md
setup.cfg
setup.py
binks/__init__.py
binks/loop.py
binks/main.py
binks/parser.py
binks/request.py
binks/response.py
binks/server.py
binks/utils.py
binks/worker.py
binks.egg-info/PKG-INFO
binks.egg-info/SOURCES.txt
binks.egg-info/dependency_links.txt
binks.egg-info/entry_points.txt
binks.egg-info/not-zip-safe
binks.egg-info/requires.txt
binks.egg-info/top_level.txt
docs/Makefile
docs/conf.py
docs/contributing.rst
docs/history.rst
docs/index.rst
docs/installation.rst
docs/make.bat
docs/readme.rst
docs/usage.rst
tests/test_binks.py