Metadata-Version: 1.1
Name: binks
Version: 0.1.4
Summary: A simple WSGI web server.
Home-page: https://github.com/Caratpine/binks
Author: xdd1874
Author-email: bepox0531@gmail.com
License: MIT license
Keywords: binks
Platform: UNKNOWN
Classifier: Development Status :: 2 - Pre-Alpha
Classifier: Intended Audience :: Developers
Classifier: License :: OSI Approved :: MIT License
Classifier: Natural Language :: English
Classifier: Programming Language :: Python :: 3.6
Classifier: Programming Language :: Python :: 3.7
